simiotics/__init__.py
simiotics/cli.py
simiotics/clients.py
simiotics/source_types.py
simiotics-0.7.0.dist-info/METADATA
simiotics-0.7.0.dist-info/WHEEL
simiotics-0.7.0.dist-info/entry_points.txt
simiotics-0.7.0.dist-info/top_level.txt
simiotics-0.7.0.dist-info/RECORD
