Metadata-Version: 2.1
Name: simiotics
Version: 0.7.0
Summary: Simiotics Python Client
Home-page: UNKNOWN
Author: Neeraj Kashyap
Author-email: neeraj@simiotics.com
License: UNKNOWN
Platform: UNKNOWN
Classifier: Development Status :: 2 - Pre-Alpha
Classifier: Programming Language :: Python :: 3
Requires-Dist: requests (<3.0.0,>=2.22.0)
